<?xml version="1.0" encoding="UTF-8"?>
<resources>

<string name="NoItemsInCategory">Não foram encontrados artigos nesta categoria</string>
<string name="IapErrorText">Ocorreu um erro inesperado. A sua compra não foi completada.</string>
<string name="XmasBox">Presente de Natal</string>
<string name="Commodity_Scraps">Restos</string>
<string name="Commodity_Artifacts">Artefactos alienígenas</string>
<string name="Commodity_Minerals">Minerais</string>
<string name="Commodity_PreciousMetals">Metais preciosos</string>
<string name="Commodity_GemStones">Pedras preciosas</string>
<string name="Commodity_Alloys">Ligas metálicas</string>
<string name="Commodity_Polymers">Polímeros</string>
<string name="Commodity_ToxicWaste">Lixo tóxico</string>

</resources>
